distributions_1107/Binomialdistribution.py
distributions_1107/Gaussiandistribution.py
distributions_1107/Generaldistribution.py
distributions_1107/__init__.py
distributions_1107-1.0.dist-info/DESCRIPTION.rst
distributions_1107-1.0.dist-info/METADATA
distributions_1107-1.0.dist-info/RECORD
distributions_1107-1.0.dist-info/WHEEL
distributions_1107-1.0.dist-info/metadata.json
distributions_1107-1.0.dist-info/top_level.txt
